setup.py
vcs2eric/__init__.py
vcs2eric/vcs2eric.py
vcs2eric.egg-info/PKG-INFO
vcs2eric.egg-info/SOURCES.txt
vcs2eric.egg-info/dependency_links.txt
vcs2eric.egg-info/entry_points.txt
vcs2eric.egg-info/not-zip-safe
vcs2eric.egg-info/top_level.txt