Metadata-Version: 1.1
Name: vcs2eric
Version: 1.0.0
Summary: Generates Eric4 IDE project files from existing VCS checkouts
Home-page: https://launchpad.net/vcs2eric
Author: Mike C. Fletcher
Author-email: mcfletch@vrplumber.com
License: GPLv3
Download-URL: https://launchpad.net/vcs2eric/+download
Keywords: vcs,bzr,cvs,svn,git,hg,eric4
Platform: Linux
Classifier: Programming Language :: Python :: 2
Classifier: Programming Language :: Python :: 3
Classifier: Topic :: Software Development :: Libraries :: Python Modules
Classifier: Intended Audience :: Developers
